{"title":"NaughtyOffice - Jennifer White, Noelle Easton (NaughtyAmerica) 7","uid":15341437,"size":1274047301,"categoryP":"porn","categoryS":"hd___movies","magnet":"?xt=urn:btih:075ecb70de3722f8051afe74973a41d6c373c387&amp;dn=NaughtyOffice+-+Jennifer+White%2C+Noelle+Easton+%28NaughtyAmerica%29+7&amp;tr=udp%3A%2F%2Ftracker.leechers-paradise.org%3A6969&amp;tr=udp%3A%2F%2Fzer0day.ch%3A1337&amp;tr=udp%3A%2F%2Fopen.demonii.com%3A1337&amp;tr=udp%3A%2F%2Ftracker.coppersurfer.tk%3A6969&amp;tr=udp%3A%2F%2Fexodus.desync.com%3A6969","seeders":1,"leechers":0,"uploader":"codho","files":1,"time":1468841104,"description":"NaughtyOffice - Jennifer White, Noelle Easton (NaughtyAmerica) 720p NEW July 18, 2016\r\n\r\n\r\nNoelle Easton has her employee, Jennifer White, service her after work. Noelle's boss walks in on them in is a little upset that he wasn't invited. Luckily the girls don't mind and have him join in.\r\n\r\n\r\n \nhttp://imgaah.com/viewer.php?file=08255071619808895409.jpg\r\n \nhttp://imgaah.com/viewer.php?file=57277912473636524198.jpg\r\n \nhttp://imgaah.com/viewer.php?file=02550516253774399583.jpeg","torrent":{"xt":"urn:btih:075ecb70de3722f8051afe74973a41d6c373c387","amp;dn":"NaughtyOffice+-+Jennifer+White%2C+Noelle+Easton+%28NaughtyAmerica%29+7","amp;tr":["udp%3A%2F%2Ftracker.leechers-paradise.org%3A6969","udp%3A%2F%2Fzer0day.ch%3A1337","udp%3A%2F%2Fopen.demonii.com%3A1337","udp%3A%2F%2Ftracker.coppersurfer.tk%3A6969","udp%3A%2F%2Fexodus.desync.com%3A6969"],"infoHash":"075ecb70de3722f8051afe74973a41d6c373c387","infoHashBuffer":{"type":"Buffer","data":[7,94,203,112,222,55,34,248,5,26,254,116,151,58,65,214,195,115,195,135]},"announce":[],"urlList":[]}}