{"title":"Gamma Ray - Master of Confusion (2013)","uid":8258686,"size":133654624,"categoryP":"audio","categoryS":"music","magnet":"?xt=urn:btih:0ac66e727eb811b2f658efbb879ada9b04591d86&amp;dn=Gamma+Ray+-+Master+of+Confusion+%282013%29&amp;tr=udp%3A%2F%2Ftracker.openbittorrent.com%3A80&amp;tr=udp%3A%2F%2Fopen.demonii.com%3A1337&amp;tr=udp%3A%2F%2Ftracker.coppersurfer.tk%3A6969&amp;tr=udp%3A%2F%2Fexodus.desync.com%3A6969","seeders":1,"leechers":0,"uploader":"BaphV13","files":10,"time":1363321565,"description":"Gamma Ray - Master of Confusion (2013)\n\nBy \n &lt;a href=&quot;\nhttp://www.BaphV13.com&quot; rel=&quot;nofollow&quot; target=&quot;_NEW&quot;&gt;\nhttp://www.BaphV13.com&lt;/a&gt;","torrent":{"xt":"urn:btih:0ac66e727eb811b2f658efbb879ada9b04591d86","amp;dn":"Gamma+Ray+-+Master+of+Confusion+%282013%29","amp;tr":["udp%3A%2F%2Ftracker.openbittorrent.com%3A80","udp%3A%2F%2Fopen.demonii.com%3A1337","udp%3A%2F%2Ftracker.coppersurfer.tk%3A6969","udp%3A%2F%2Fexodus.desync.com%3A6969"],"infoHash":"0ac66e727eb811b2f658efbb879ada9b04591d86","infoHashBuffer":{"type":"Buffer","data":[10,198,110,114,126,184,17,178,246,88,239,187,135,154,218,155,4,89,29,134]},"announce":[],"urlList":[]}}