{"title":"secret diary of a call girl s01","uid":3917948,"size":1457645568,"categoryP":"video","categoryS":"tv_shows","magnet":"?xt=urn:btih:0e4379b4dde453020dbeb5073197a310ff4457e9&amp;dn=secret+diary+of+a+call+girl+s01&amp;tr=udp%3A%2F%2Ftracker.openbittorrent.com%3A80&amp;tr=udp%3A%2F%2Fopen.demonii.com%3A1337&amp;tr=udp%3A%2F%2Ftracker.coppersurfer.tk%3A6969&amp;tr=udp%3A%2F%2Fexodus.desync.com%3A6969","seeders":1,"leechers":0,"uploader":"yourpcguy73","files":8,"time":1196605369,"description":"secret diary of a call girl s01\n\ncomplete\n\ni havent had time to watch them yet.\n\nthere from a private tracker so im sure there good tho.\n","torrent":{"xt":"urn:btih:0e4379b4dde453020dbeb5073197a310ff4457e9","amp;dn":"secret+diary+of+a+call+girl+s01","amp;tr":["udp%3A%2F%2Ftracker.openbittorrent.com%3A80","udp%3A%2F%2Fopen.demonii.com%3A1337","udp%3A%2F%2Ftracker.coppersurfer.tk%3A6969","udp%3A%2F%2Fexodus.desync.com%3A6969"],"infoHash":"0e4379b4dde453020dbeb5073197a310ff4457e9","infoHashBuffer":{"type":"Buffer","data":[14,67,121,180,221,228,83,2,13,190,181,7,49,151,163,16,255,68,87,233]},"announce":[],"urlList":[]}}