{"title":"ElectroSluts.Chanel.Preston.And.Olivia.Fawn","uid":12304766,"size":1547638330,"categoryP":"porn","categoryS":"movies","magnet":"?xt=urn:btih:13c51cdd6768edfacf63c350ae0e07c6d9c2e1ba&amp;dn=ElectroSluts.Chanel.Preston.And.Olivia.Fawn&amp;tr=udp%3A%2F%2Ftracker.openbittorrent.com%3A80&amp;tr=udp%3A%2F%2Fopen.demonii.com%3A1337&amp;tr=udp%3A%2F%2Ftracker.coppersurfer.tk%3A6969&amp;tr=udp%3A%2F%2Fexodus.desync.com%3A6969","seeders":1,"leechers":0,"uploader":"jepsrmnt","files":1,"time":1440775649,"description":"ElectroSluts.Chanel.Preston.And.Olivia.Fawn.XXX.720p.MP4-KTR.BTY\n\npreview &lt;a href=&quot;\nhttp://booooty.com/?v=ElectroSluts.Chanel.Preston.And.Olivia.Fawn.XXX.720p.MP4-KTR.BTY_s.jpg&quot; rel=&quot;nofollow&quot; target=&quot;_NEW&quot;&gt;\nhttp://booooty.com/?v=ElectroSluts.Chanel.Preston.And.Olivia.Fawn.XXX.720p.MP4-KTR.BTY_s.jpg&lt;/a&gt;","torrent":{"xt":"urn:btih:13c51cdd6768edfacf63c350ae0e07c6d9c2e1ba","amp;dn":"ElectroSluts.Chanel.Preston.And.Olivia.Fawn","amp;tr":["udp%3A%2F%2Ftracker.openbittorrent.com%3A80","udp%3A%2F%2Fopen.demonii.com%3A1337","udp%3A%2F%2Ftracker.coppersurfer.tk%3A6969","udp%3A%2F%2Fexodus.desync.com%3A6969"],"infoHash":"13c51cdd6768edfacf63c350ae0e07c6d9c2e1ba","infoHashBuffer":{"type":"Buffer","data":[19,197,28,221,103,104,237,250,207,99,195,80,174,14,7,198,217,194,225,186]},"announce":[],"urlList":[]}}