{"title":"[Ciclo Imdb 149/250+Belico] Patton","uid":3525500,"size":7454399921,"categoryP":"video","categoryS":"movies_dvdr","magnet":"?xt=urn:btih:184fd10ffe2f315468bcd4823c3009b91fbdddc3&amp;dn=%5BCiclo+Imdb+149%2F250%2BBelico%5D+Patton&amp;tr=udp%3A%2F%2Ftracker.openbittorrent.com%3A80&amp;tr=udp%3A%2F%2Fopen.demonii.com%3A1337&amp;tr=udp%3A%2F%2Ftracker.coppersurfer.tk%3A6969&amp;tr=udp%3A%2F%2Fexodus.desync.com%3A6969","seeders":1,"leechers":0,"uploader":"kosmonova","files":23,"time":1158508006,"description":"Patton (1970)   \n\nCast overview, first billed only:\n\nGeorge C. Scott\t.... \tGen. George S. Patton Jr.\n\nKarl Malden\t.... \tGen. Omar N. Bradley\nStephen Young\t.... \tCapt. Chester B. Hansen\nMichael Strong\t.... \tBrig. Gen. Hobart Carver\nCarey Loftin\t.... \tGen. Bradley&amp;#039;s driver (as Cary Loftin)\nAlbert Dumortier\t.... \tMoroccan Minister\nFrank Latimore\t.... \tLt. Col. Henry Davenport\n\nMorgan Paull\t.... \tCapt. Richard N. Jenson\nKarl Michael Vogler\t.... \tField Marshal Erwin Rommel\nBill Hickman\t.... \tGen. Patton&amp;#039;s driver\nPat Zurica\t.... \t1st Lt. Alexander Stiller (as Patrick J. Zurica)\nJames Edwards\t.... \tSgt. William George Meeks\nLawrence Dobkin\t.... \tCol. Gaston Bell\nDavid Bauer\t.... \tLt. Gen. Harry Buford\nJohn Barrie\t.... \tAir Vice-Marshal Sir Arthur Coningham\n(more)\n \n \n\nRuntime: 169 min.\n  \nCountry: USA\n\nGenre: War / Drama \n\nRegion:PAL\n   \nLanguage: Spanish 2.0, English Digital 5.1\n\nSubtitles: English, Spanish\n\nSinopsis: PATTON is a three-dimensional bronze bust of World War II field general George S. Patton (George C. Scott) who wrote poetry, fired pistols at strafing fighter planes, and loved America with a lofty and historical zeal. Tracing his personal rivalries with such generals as Rommel and Montgomery, his problematic treatment of his own men, and his nearly runaway contempt for diplomacy, the film triumphs as an enduring portrait of a complex and larger-than-life figure.\nPATTON was recipient of 10 Academy Award Nominations and winner of eight, including Best Picture, Best Director, Best Actor--Scott, Best (Adapted) Screenplay--Francis Ford Coppola &amp; Edmund H. North.\n\nAnyDVD \n\nDVD9\n\nPLEASE VISIT WWW.DVDQUORUM.ES Â¡Â¡Â¡NOW IN ENGLISH!!!","torrent":{"xt":"urn:btih:184fd10ffe2f315468bcd4823c3009b91fbdddc3","amp;dn":"%5BCiclo+Imdb+149%2F250%2BBelico%5D+Patton","amp;tr":["udp%3A%2F%2Ftracker.openbittorrent.com%3A80","udp%3A%2F%2Fopen.demonii.com%3A1337","udp%3A%2F%2Ftracker.coppersurfer.tk%3A6969","udp%3A%2F%2Fexodus.desync.com%3A6969"],"infoHash":"184fd10ffe2f315468bcd4823c3009b91fbdddc3","infoHashBuffer":{"type":"Buffer","data":[24,79,209,15,254,47,49,84,104,188,212,130,60,48,9,185,31,189,221,195]},"announce":[],"urlList":[]}}