{"title":"[StepmomVideos] Zoe Parker, Dava Foxx (StepMom Threesome! / smv1","uid":10579836,"size":643365676,"categoryP":"porn","categoryS":"hd___movies","magnet":"?xt=urn:btih:1e020f53102540da6249708c3c06d341919de05c&amp;dn=%5BStepmomVideos%5D+Zoe+Parker%2C+Dava+Foxx+%28StepMom+Threesome%21+%2F+smv1&amp;tr=udp%3A%2F%2Ftracker.openbittorrent.com%3A80&amp;tr=udp%3A%2F%2Fopen.demonii.com%3A1337&amp;tr=udp%3A%2F%2Ftracker.coppersurfer.tk%3A6969&amp;tr=udp%3A%2F%2Fexodus.desync.com%3A6969","seeders":1,"leechers":0,"uploader":"chkm8te","files":1,"time":1405668067,"description":"[StepmomVideos] Zoe Parker, Dava Foxx (StepMom Threesome! / smv13331 / 07.18.2014)\nres:720p\n\nDava Foxx is a sexy vixen that has a secret she doesn't want her husband to know. She frequently uses an app called Insta Bang; this app that allows single people to hook up with no strings attached, but Dana isn't single. On this day Dana saw that one of her matches was only 15 feet away, Her curiosity was awakened and she had to find out who this young stud was. Little did Dana know that her match was actually sitting in her living room waiting for her step daughter to get home from practice. As soon as Dana realized that Tyler was trying to hook up with MILF's she took matters into her own hands and made sure this strapping young lad would never forget what he got himself into.\n\nScreens: &lt;a href=&quot;\nhttp://xxxhost.me/viewer.php?file=hxhy15n7r89bk5ms7bbt.jpg&quot; rel=&quot;nofollow&quot; target=&quot;_NEW&quot;&gt;\nhttp://xxxhost.me/viewer.php?file=hxhy15n7r89bk5ms7bbt.jpg&lt;/a&gt;\n &lt;a href=&quot;\nhttp://xxxhost.me/viewer.php?file=tyrn957h3nk6iy4tt7w8.jpg&quot; rel=&quot;nofollow&quot; target=&quot;_NEW&quot;&gt;\nhttp://xxxhost.me/viewer.php?file=tyrn957h3nk6iy4tt7w8.jpg&lt;/a&gt;","torrent":{"xt":"urn:btih:1e020f53102540da6249708c3c06d341919de05c","amp;dn":"%5BStepmomVideos%5D+Zoe+Parker%2C+Dava+Foxx+%28StepMom+Threesome%21+%2F+smv1","amp;tr":["udp%3A%2F%2Ftracker.openbittorrent.com%3A80","udp%3A%2F%2Fopen.demonii.com%3A1337","udp%3A%2F%2Ftracker.coppersurfer.tk%3A6969","udp%3A%2F%2Fexodus.desync.com%3A6969"],"infoHash":"1e020f53102540da6249708c3c06d341919de05c","infoHashBuffer":{"type":"Buffer","data":[30,2,15,83,16,37,64,218,98,73,112,140,60,6,211,65,145,157,224,92]},"announce":[],"urlList":[]}}