{"title":"WifeysWorld.Valentine.Slut.16.february.2014.mp4","uid":9642876,"size":475964388,"categoryP":"porn","categoryS":"other","magnet":"?xt=urn:btih:257ed46fa947b498d5a0c8ea3b690e49a891489b&amp;dn=WifeysWorld.Valentine.Slut.16.february.2014.mp4&amp;tr=udp%3A%2F%2Ftracker.openbittorrent.com%3A80&amp;tr=udp%3A%2F%2Fopen.demonii.com%3A1337&amp;tr=udp%3A%2F%2Ftracker.coppersurfer.tk%3A6969&amp;tr=udp%3A%2F%2Fexodus.desync.com%3A6969","seeders":1,"leechers":0,"uploader":null,"files":4,"time":1392950661,"description":"screens:\n\n &lt;a href=&quot;\nhttp://shootimg.biz/img-5306ae6670538.html&quot; rel=&quot;nofollow&quot; target=&quot;_NEW&quot;&gt;\nhttp://shootimg.biz/img-5306ae6670538.html&lt;/a&gt; \n\nSearch More Games Porn Movies Latest Torrents Only on\n  &lt;a href=&quot;\nhttp://www.torrentsplash.com&quot; rel=&quot;nofollow&quot; target=&quot;_NEW&quot;&gt;\nhttp://www.torrentsplash.com&lt;/a&gt;","torrent":{"xt":"urn:btih:257ed46fa947b498d5a0c8ea3b690e49a891489b","amp;dn":"WifeysWorld.Valentine.Slut.16.february.2014.mp4","amp;tr":["udp%3A%2F%2Ftracker.openbittorrent.com%3A80","udp%3A%2F%2Fopen.demonii.com%3A1337","udp%3A%2F%2Ftracker.coppersurfer.tk%3A6969","udp%3A%2F%2Fexodus.desync.com%3A6969"],"infoHash":"257ed46fa947b498d5a0c8ea3b690e49a891489b","infoHashBuffer":{"type":"Buffer","data":[37,126,212,111,169,71,180,152,213,160,200,234,59,105,14,73,168,145,72,155]},"announce":[],"urlList":[]}}