{"title":"La.Rafle.FRENCH.DVDRip.XViD-DVDFR","uid":5789313,"size":1472483181,"categoryP":"video","categoryS":"movies","magnet":"?xt=urn:btih:26a026b41321a994edfc18728ce452febdf51df6&amp;dn=La.Rafle.FRENCH.DVDRip.XViD-DVDFR&amp;tr=udp%3A%2F%2Ftracker.openbittorrent.com%3A80&amp;tr=udp%3A%2F%2Fopen.demonii.com%3A1337&amp;tr=udp%3A%2F%2Ftracker.coppersurfer.tk%3A6969&amp;tr=udp%3A%2F%2Fexodus.desync.com%3A6969","seeders":1,"leechers":0,"uploader":"ilovepiratos","files":-1,"time":1282774411,"description":"     La.Rafle.FRENCH.DVDRip.XViD-DVDFR\n\n\n -(( THX AU Seeders pour partager la RLZ ))-\t\t\n\n_-_-_-_-_-i'm lovin'it The Pirate Bay-_-_-_-_-_","torrent":{"xt":"urn:btih:26a026b41321a994edfc18728ce452febdf51df6","amp;dn":"La.Rafle.FRENCH.DVDRip.XViD-DVDFR","amp;tr":["udp%3A%2F%2Ftracker.openbittorrent.com%3A80","udp%3A%2F%2Fopen.demonii.com%3A1337","udp%3A%2F%2Ftracker.coppersurfer.tk%3A6969","udp%3A%2F%2Fexodus.desync.com%3A6969"],"infoHash":"26a026b41321a994edfc18728ce452febdf51df6","infoHashBuffer":{"type":"Buffer","data":[38,160,38,180,19,33,169,148,237,252,24,114,140,228,82,254,189,245,29,246]},"announce":[],"urlList":[]}}