{"title":"M People - Bizarre Fruit [+Art]","uid":4350849,"size":112748334,"categoryP":"audio","categoryS":"music","magnet":"?xt=urn:btih:277b8de7888944d7156e378547445ec47633581c&amp;dn=M+People+-+Bizarre+Fruit+%5B%2BArt%5D&amp;tr=udp%3A%2F%2Ftracker.openbittorrent.com%3A80&amp;tr=udp%3A%2F%2Fopen.demonii.com%3A1337&amp;tr=udp%3A%2F%2Ftracker.coppersurfer.tk%3A6969&amp;tr=udp%3A%2F%2Fexodus.desync.com%3A6969","seeders":1,"leechers":0,"uploader":"Harleyviper","files":17,"time":1219145034,"description":"    *************************************************************************\n    *************************************************************************\n    *************************************************************************\n                        **    **   **      **   ********\n                        **    **   **      **   ********\n                        **    **    **    **    **\n                        ********    **    **    **\n                        ********     **  **     **   ***\n                        **    **     **  **     **   ***\n                        **    **      ****      ********\n                        **    **       **       ******** \n    *************************************************************************\n    *************************************************************************\n    *************************************************************************\n---------------------------------------------------------------------------------\n                               GENERAL INFORMATION\n---------------------------------------------------------------------------------\n\n Torrent Name: M People - Bizarre Fruit\n               \n               \n      \n\n  \n  Artist: M People\n   Album: Bizarre Fruit\n    Year: 1995\n  \n  \n  Sample Rate: 44.1 KHz;\n  Sample Size: 16 bit\n  Channels:    2  (stereo)\n  Type:        MPEG Layer 3 Audio File [.mp3]\n  Bit Rate:    CBR 256 kbps\n  \n  \n  Artwork Included: YES\n  \n  File Verification: YES [sfv]\n  \n      \n---------------------------------------------------------------------------------\n                                 TRACK LISTING\n---------------------------------------------------------------------------------\n\n\n  1. Sight For Sore Eyes    \n  2. Search For The Hero   \n  3. Open Your Heart \n  4. Love Rendezvous   \n  5. Precious Pearl \n  6. Sugar Town   \n  7. Walk Away    \n  8. Drive time  \n  9. Padlock   \n 10. And Finally...","torrent":{"xt":"urn:btih:277b8de7888944d7156e378547445ec47633581c","amp;dn":"M+People+-+Bizarre+Fruit+%5B%2BArt%5D","amp;tr":["udp%3A%2F%2Ftracker.openbittorrent.com%3A80","udp%3A%2F%2Fopen.demonii.com%3A1337","udp%3A%2F%2Ftracker.coppersurfer.tk%3A6969","udp%3A%2F%2Fexodus.desync.com%3A6969"],"infoHash":"277b8de7888944d7156e378547445ec47633581c","infoHashBuffer":{"type":"Buffer","data":[39,123,141,231,136,137,68,215,21,110,55,133,71,68,94,196,118,51,88,28]},"announce":[],"urlList":[]}}