{"title":"The Society Of Invisibles - 2006 - full album","uid":10509695,"size":56059817,"categoryP":"audio","categoryS":"music","magnet":"?xt=urn:btih:2d341631651409f53a17f9c33f4401fb60b83208&amp;dn=The+Society+Of+Invisibles+-+2006+-+full+album&amp;tr=udp%3A%2F%2Ftracker.openbittorrent.com%3A80&amp;tr=udp%3A%2F%2Fopen.demonii.com%3A1337&amp;tr=udp%3A%2F%2Ftracker.coppersurfer.tk%3A6969&amp;tr=udp%3A%2F%2Fexodus.desync.com%3A6969","seeders":1,"leechers":0,"uploader":"Argbatman","files":-1,"time":1404829988,"description":"This is the full album of the society of invisibles.\n\n&quot; A notorious group/movement hailing from Phoenix, Arizona, the Society of Invisibles consist of the cream of the crop emcees and producers. The Invisibles are the perfect mixture of street science, horrorcore lyricism, and hardcore hip-hop.\n\nFacecrushers, Inc., Darkwater, solo acts Terminator Tragic, Sneaky Pete, Rok, and the in-house production team The Dead Beats all united to form the best of the Southwest's regional independent talent. The Society of the Invisibles have toured with Jedi Mind Tricks, Non-Phixion, Wu-Tang Clan amongst others.\n\nStylistically comparable to the indie hip-hop 'horrorcore' elite such as Jedi Mind Tricks, Necro, Ill Bill, Non-Phixion and more, The Society of Invisibles are the foremost pioneering talent of an upcoming generation of independent hip-hop.\nthe society of invisibles is signed by Babygrande records with the likes of immortal technique and jedi mind tricks. &quot;\n\nIf you ask I also have the Rare cuts from Vol.1 to Vol. 7. and I can upload them.\n\n Tracklist\n\nIntro \t        1:55\nDial M For Murder 3:57\nWatching You \t4:30\nCaleb Winner \t4:09\nDown    \t2:50\nDead Beat 1 \t0:35\nBerzerk \t1:08\nNothing Worse \t4:39\nRoknowledge \t1:48\nRobbery \t1:24\nHack Pack \t4:32\nDead Beat 2 \t0:44\nGoose Bumps \t4:01\nCarpe Diem \t1:41\nHardcore \t2:29\nTech Connect \t3:02\nOutro \t        1:20\n\nBonus Track\nOn My Way\n\n","torrent":{"xt":"urn:btih:2d341631651409f53a17f9c33f4401fb60b83208","amp;dn":"The+Society+Of+Invisibles+-+2006+-+full+album","amp;tr":["udp%3A%2F%2Ftracker.openbittorrent.com%3A80","udp%3A%2F%2Fopen.demonii.com%3A1337","udp%3A%2F%2Ftracker.coppersurfer.tk%3A6969","udp%3A%2F%2Fexodus.desync.com%3A6969"],"infoHash":"2d341631651409f53a17f9c33f4401fb60b83208","infoHashBuffer":{"type":"Buffer","data":[45,52,22,49,101,20,9,245,58,23,249,195,63,68,1,251,96,184,50,8]},"announce":[],"urlList":[]}}