{"title":"Conan.2011.08.02.Shaquille.ONeal.720p.HDTV.x264-MOMENTUM","uid":6579838,"size":892361917,"categoryP":"video","categoryS":"hd___tv_shows","magnet":"?xt=urn:btih:46cb73494b409048cfe1b01f354cba26cb87f920&amp;dn=Conan.2011.08.02.Shaquille.ONeal.720p.HDTV.x264-MOMENTUM&amp;tr=udp%3A%2F%2Ftracker.openbittorrent.com%3A80&amp;tr=udp%3A%2F%2Fopen.demonii.com%3A1337&amp;tr=udp%3A%2F%2Ftracker.coppersurfer.tk%3A6969&amp;tr=udp%3A%2F%2Fexodus.desync.com%3A6969","seeders":1,"leechers":0,"uploader":"sceneline","files":22,"time":1312362091,"description":"- &lt;a href=&quot;\nhttp://www.Speed.Cd&quot; rel=&quot;nofollow&quot; target=&quot;_NEW&quot;&gt;\nhttp://www.Speed.Cd&lt;/a&gt;\n &lt;a href=&quot;\nhttp://www.Speed.Cd&quot; rel=&quot;nofollow&quot; target=&quot;_NEW&quot;&gt;\nhttp://www.Speed.Cd&lt;/a&gt;      fast  and The Hottest Private Tracker on the net\n\n(((--Registration will open on june every weekend--)))\n\nPlease Seed back to make the speed Faster!!!\n\nand don't forget to visit .......http://www.Speed.Cd  ......\n\n\n ............ NFO .............\n-Conan.2011.08.02.Shaquille.ONeal.720p.HDTV.x264-MOMENTUM\n\nRelease Date.....: 2011-08-03\nFilesize.........: 851.0MB\nRuntime..........: 00:42:03\nVideo............: 2324kbps x264\nAudio............: 448kbps AC3 6ch\nFrame Size.......: 1280x720\nFrame Rate.......: 59.940","torrent":{"xt":"urn:btih:46cb73494b409048cfe1b01f354cba26cb87f920","amp;dn":"Conan.2011.08.02.Shaquille.ONeal.720p.HDTV.x264-MOMENTUM","amp;tr":["udp%3A%2F%2Ftracker.openbittorrent.com%3A80","udp%3A%2F%2Fopen.demonii.com%3A1337","udp%3A%2F%2Ftracker.coppersurfer.tk%3A6969","udp%3A%2F%2Fexodus.desync.com%3A6969"],"infoHash":"46cb73494b409048cfe1b01f354cba26cb87f920","infoHashBuffer":{"type":"Buffer","data":[70,203,115,73,75,64,144,72,207,225,176,31,53,76,186,38,203,135,249,32]},"announce":[],"urlList":[]}}