{"title":"Apps Magazine Issue 49 - 2014  UK","uid":10771576,"size":14068342,"categoryP":"other","categoryS":"e_books","magnet":"?xt=urn:btih:5184b757a2d322e38518e2ff4beaeb30be5c36fa&amp;dn=Apps+Magazine+Issue+49+-+2014++UK&amp;tr=udp%3A%2F%2Ftracker.openbittorrent.com%3A80&amp;tr=udp%3A%2F%2Fopen.demonii.com%3A1337&amp;tr=udp%3A%2F%2Ftracker.coppersurfer.tk%3A6969&amp;tr=udp%3A%2F%2Fexodus.desync.com%3A6969","seeders":1,"leechers":0,"uploader":"tbohana","files":-1,"time":1408085551,"description":"\nApps Magazine Issue 49 - 2014  UK\n\n50 Pages | True PDF | English | 13 MB \n\n\nThe first magazine of its kind, Apps Magazine will be dedicated to matching the incredible demand for the latest and greatest App Store products with expert buying advice for a broad range of readers. With reviews of apps from all categories, as well as group tests, features and tutorials, Apps Magazine is the ultimate resource for anyone looking to download any of the 250,000 apps currently available.\n\n\n","torrent":{"xt":"urn:btih:5184b757a2d322e38518e2ff4beaeb30be5c36fa","amp;dn":"Apps+Magazine+Issue+49+-+2014++UK","amp;tr":["udp%3A%2F%2Ftracker.openbittorrent.com%3A80","udp%3A%2F%2Fopen.demonii.com%3A1337","udp%3A%2F%2Ftracker.coppersurfer.tk%3A6969","udp%3A%2F%2Fexodus.desync.com%3A6969"],"infoHash":"5184b757a2d322e38518e2ff4beaeb30be5c36fa","infoHashBuffer":{"type":"Buffer","data":[81,132,183,87,162,211,34,227,133,24,226,255,75,234,235,48,190,92,54,250]},"announce":[],"urlList":[]}}