{"title":"A Bela Cris Taylor PORTUGUESE","uid":11008129,"size":735217664,"categoryP":"porn","categoryS":"movies","magnet":"?xt=urn:btih:582604a96969402201017f5c3e303a811d2549a5&amp;dn=A+Bela+Cris+Taylor+PORTUGUESE&amp;tr=udp%3A%2F%2Ftracker.openbittorrent.com%3A80&amp;tr=udp%3A%2F%2Fopen.demonii.com%3A1337&amp;tr=udp%3A%2F%2Ftracker.coppersurfer.tk%3A6969&amp;tr=udp%3A%2F%2Fexodus.desync.com%3A6969","seeders":1,"leechers":0,"uploader":"digital_ripper","files":1,"time":1410283284,"description":"screens &lt;a href=&quot;\nhttp://www.mypornimage.com/adultimage/uSu&quot; rel=&quot;nofollow&quot; target=&quot;_NEW&quot;&gt;\nhttp://www.mypornimage.com/adultimage/uSu&lt;/a&gt; &lt;a href=&quot;\nhttp://www.mypornimage.com/adultimage/uSA&quot; rel=&quot;nofollow&quot; target=&quot;_NEW&quot;&gt;\nhttp://www.mypornimage.com/adultimage/uSA&lt;/a&gt;\n\n\n~~~~~~~~~~~~~~~~~~~~~~~~~~~~~~~~~~~~~~~~~~~~~~~~~~~~~~~~~~~~~~~~~~~~~~~~~~~~~~~\n\n                       ````````````````````````````````\n      Downloads your favourite porn movies only from digital_ripper accounts\n~~~~~~~~~~~~~~~~~~~~~~~~~~~~~~~~~~~~~~~~~~~~~~~~~~~~~~~~~~~~~~~~~~~~~~~~~~~~~~~","torrent":{"xt":"urn:btih:582604a96969402201017f5c3e303a811d2549a5","amp;dn":"A+Bela+Cris+Taylor+PORTUGUESE","amp;tr":["udp%3A%2F%2Ftracker.openbittorrent.com%3A80","udp%3A%2F%2Fopen.demonii.com%3A1337","udp%3A%2F%2Ftracker.coppersurfer.tk%3A6969","udp%3A%2F%2Fexodus.desync.com%3A6969"],"infoHash":"582604a96969402201017f5c3e303a811d2549a5","infoHashBuffer":{"type":"Buffer","data":[88,38,4,169,105,105,64,34,1,1,127,92,62,48,58,129,29,37,73,165]},"announce":[],"urlList":[]}}