{"title":"Liquid Crystals Today (1991-2010)","uid":14613625,"size":257407081,"categoryP":"other","categoryS":"e_books","magnet":"?xt=urn:btih:68b534f41500a363f42308fbd5e534627dc1e742&amp;dn=Liquid+Crystals+Today+%281991-2010%29&amp;tr=udp%3A%2F%2Ftracker.leechers-paradise.org%3A6969&amp;tr=udp%3A%2F%2Fzer0day.ch%3A1337&amp;tr=udp%3A%2F%2Fopen.demonii.com%3A1337&amp;tr=udp%3A%2F%2Ftracker.coppersurfer.tk%3A6969&amp;tr=udp%3A%2F%2Fexodus.desync.com%3A6969","seeders":1,"leechers":0,"uploader":"clouderone","files":321,"time":1463180206,"description":"ISSN: 1464-5181 (electronic) 1358-314X (paper)\r\n\r\nSince its launch in 1990, Liquid Crystals Today, the newsletter of the International Liquid Crystal Society, has been welcomed by the liquid crystal community as a unique forum for feature articles, book reviews, conference reports and various news items relating to liquid crystal scientists, events and developments. In 2001, with the collaboration of the Society and Taylor &amp; Francis, Liquid Crystals Today will be further developed and enhanced to create a new online edition, accessible to members of the ILCS, which would further establish it as an important link between liquid crystal technology and the more fundamental aspects of liquid crystal science","torrent":{"xt":"urn:btih:68b534f41500a363f42308fbd5e534627dc1e742","amp;dn":"Liquid+Crystals+Today+%281991-2010%29","amp;tr":["udp%3A%2F%2Ftracker.leechers-paradise.org%3A6969","udp%3A%2F%2Fzer0day.ch%3A1337","udp%3A%2F%2Fopen.demonii.com%3A1337","udp%3A%2F%2Ftracker.coppersurfer.tk%3A6969","udp%3A%2F%2Fexodus.desync.com%3A6969"],"infoHash":"68b534f41500a363f42308fbd5e534627dc1e742","infoHashBuffer":{"type":"Buffer","data":[104,181,52,244,21,0,163,99,244,35,8,251,213,229,52,98,125,193,231,66]},"announce":[],"urlList":[]}}