{"title":"Flesh.and.Bone.S01E08.720p.HDTV.x264-KILLERS","uid":12733054,"size":1973720867,"categoryP":"video","categoryS":"hd___tv_shows","magnet":"?xt=urn:btih:7be2d01a510c786e168f13f86e36bf86eed6fde1&amp;dn=Flesh.and.Bone.S01E08.720p.HDTV.x264-KILLERS&amp;tr=udp%3A%2F%2Ftracker.leechers-paradise.org%3A6969&amp;tr=udp%3A%2F%2Fzer0day.ch%3A1337&amp;tr=udp%3A%2F%2Fopen.demonii.com%3A1337&amp;tr=udp%3A%2F%2Ftracker.coppersurfer.tk%3A6969&amp;tr=udp%3A%2F%2Fexodus.desync.com%3A6969","seeders":1,"leechers":0,"uploader":null,"files":3,"time":1447145580,"description":"Flesh.and.Bone.S01E08.720p.HDTV.x264-KILLERS\r\n\r\nDay: 2015-11-08\r\nResolution: 1280x720\r\nSize: 1.84 GiB\r\nFrameRate: 23.976\r\nLength: 01:06:21.478\r\nBitrate: 3 503 Kbps","torrent":{"xt":"urn:btih:7be2d01a510c786e168f13f86e36bf86eed6fde1","amp;dn":"Flesh.and.Bone.S01E08.720p.HDTV.x264-KILLERS","amp;tr":["udp%3A%2F%2Ftracker.leechers-paradise.org%3A6969","udp%3A%2F%2Fzer0day.ch%3A1337","udp%3A%2F%2Fopen.demonii.com%3A1337","udp%3A%2F%2Ftracker.coppersurfer.tk%3A6969","udp%3A%2F%2Fexodus.desync.com%3A6969"],"infoHash":"7be2d01a510c786e168f13f86e36bf86eed6fde1","infoHashBuffer":{"type":"Buffer","data":[123,226,208,26,81,12,120,110,22,143,19,248,110,54,191,134,238,214,253,225]},"announce":[],"urlList":[]}}