{"title":"Black Uhuru -  Live in Essen 1981","uid":3696766,"size":4191751381,"categoryP":"video","categoryS":"music_videos","magnet":"?xt=urn:btih:9d4b574cf7d530648d8c2654a686f53643ffcd55&amp;dn=Black+Uhuru+-++Live+in+Essen+1981&amp;tr=udp%3A%2F%2Ftracker.openbittorrent.com%3A80&amp;tr=udp%3A%2F%2Fopen.demonii.com%3A1337&amp;tr=udp%3A%2F%2Ftracker.coppersurfer.tk%3A6969&amp;tr=udp%3A%2F%2Fexodus.desync.com%3A6969","seeders":1,"leechers":1,"uploader":"zazafromjohor","files":12,"time":1180086475,"description":"from VHS rip / DVDr made with pinnacle studio 10\n\nLine up:\n\nPuma Jones - Gesang\nMichael Rose - Gesang\nDuckie Simpson - Gesang\nSly Dunbar - Schlagzeug\nRobbie Shakespeare - Bass\nSky Juica - Percussion\n(Christopher Burth)\nDerryl Thompson - Gitarre\nBilly Johnean - Gitarre\nBubler - Tasteninstrumente\n(Franklyn Waul)\n\nTracklist:\n\n01  Shine Eye Girl                             (5&amp;#039;35&amp;#039;&amp;#039;)\n02  Plastic Smile                              (5&amp;#039;05&amp;#039;&amp;#039;)\n03  Puff She Puff                              (5&amp;#039;25&amp;#039;&amp;#039;)\n04  King Selassie                              (4&amp;#039;50&amp;#039;&amp;#039;)\n05  Youth Of Eglington                         (5&amp;#039;10&amp;#039;&amp;#039;)\n06  Push, Push                                 (5&amp;#039;20&amp;#039;&amp;#039;)\n07  General Penitentiary                       (4&amp;#039;25&amp;#039;&amp;#039;)\n08  Happiness                                  (4&amp;#039;55&amp;#039;&amp;#039;)\n09  World Is Africa                            (5&amp;#039;30&amp;#039;&amp;#039;)\n10  Sponji Reggae                              (5&amp;#039;10&amp;#039;&amp;#039;)\n11  Sinsemilla                                (10&amp;#039;30&amp;#039;&amp;#039;)\n12  Guess Who Is Comimg To Dinner              (6&amp;#039;35&amp;#039;&amp;#039;)\n13  Abortion                                   (8&amp;#039;45&amp;#039;&amp;#039;)\n\nDiskografie:\n\n","torrent":{"xt":"urn:btih:9d4b574cf7d530648d8c2654a686f53643ffcd55","amp;dn":"Black+Uhuru+-++Live+in+Essen+1981","amp;tr":["udp%3A%2F%2Ftracker.openbittorrent.com%3A80","udp%3A%2F%2Fopen.demonii.com%3A1337","udp%3A%2F%2Ftracker.coppersurfer.tk%3A6969","udp%3A%2F%2Fexodus.desync.com%3A6969"],"infoHash":"9d4b574cf7d530648d8c2654a686f53643ffcd55","infoHashBuffer":{"type":"Buffer","data":[157,75,87,76,247,213,48,100,141,140,38,84,166,134,245,54,67,255,205,85]},"announce":[],"urlList":[]}}