{"title":"Audio Book - Bloom, Allan - The Closing of the American Mind","uid":3908478,"size":217109970,"categoryP":"audio","categoryS":"audio_books","magnet":"?xt=urn:btih:a7234b6edf4f9daf5d55a266b1ee8fd8bacef199&amp;dn=Audio+Book+-+Bloom%2C+Allan+-+The+Closing+of+the+American+Mind&amp;tr=udp%3A%2F%2Ftracker.openbittorrent.com%3A80&amp;tr=udp%3A%2F%2Fopen.demonii.com%3A1337&amp;tr=udp%3A%2F%2Ftracker.coppersurfer.tk%3A6969&amp;tr=udp%3A%2F%2Fexodus.desync.com%3A6969","seeders":1,"leechers":0,"uploader":"cosisf","files":1,"time":1195996934,"description":"Audio Book - Bloom, Allan - The Closing of the American Mind.rar","torrent":{"xt":"urn:btih:a7234b6edf4f9daf5d55a266b1ee8fd8bacef199","amp;dn":"Audio+Book+-+Bloom%2C+Allan+-+The+Closing+of+the+American+Mind","amp;tr":["udp%3A%2F%2Ftracker.openbittorrent.com%3A80","udp%3A%2F%2Fopen.demonii.com%3A1337","udp%3A%2F%2Ftracker.coppersurfer.tk%3A6969","udp%3A%2F%2Fexodus.desync.com%3A6969"],"infoHash":"a7234b6edf4f9daf5d55a266b1ee8fd8bacef199","infoHashBuffer":{"type":"Buffer","data":[167,35,75,110,223,79,157,175,93,85,162,102,177,238,143,216,186,206,241,153]},"announce":[],"urlList":[]}}