{"title":"Dansband-Thor Görans-40 År På Vägarna","uid":14584443,"size":277282575,"categoryP":"audio","categoryS":"music","magnet":"?xt=urn:btih:a9d2393a7f1c1a0f212727d768847ee3a02b02f6&amp;dn=Dansband-Thor+G%26ouml%3Brans-40+%26Aring%3Br+P%26aring%3B+V%26auml%3Bgarna&amp;tr=udp%3A%2F%2Ftracker.leechers-paradise.org%3A6969&amp;tr=udp%3A%2F%2Fzer0day.ch%3A1337&amp;tr=udp%3A%2F%2Fopen.demonii.com%3A1337&amp;tr=udp%3A%2F%2Ftracker.coppersurfer.tk%3A6969&amp;tr=udp%3A%2F%2Fexodus.desync.com%3A6969","seeders":1,"leechers":0,"uploader":null,"files":41,"time":1462906098,"description":"01,Kärlek Över Nätet-Thor Görans (3:42)\r\n    02,Ge Mig, Ge Mig-Thor Görans (3:15)\r\n    03,Jag Ska Ge Dig Tusen Rosor-Thor Görans (2:33)\r\n    04,Det Är Okej, Bara Du Älskar Mig-Thor Görans (3:43)\r\n    05,Tro På Mig-Thor Görans (4:02)\r\n    06,Ge Mig En Chans-Thor Görans (2:31)\r\n    07,Störst Av Är Ändå Kärleken-Thor Görans (3:17)\r\n    08,En Kvinna Och En Man-Thor Görans (2:32)\r\n    09,Vi Ska Alltid Vara Tillsammans-Thor Görans (3:43)\r\n    10,Lyckans Dag-Thor Görans (2:49)\r\n    11,Kär I Dig-Thor Görans (3:04)\r\n    12,En På Miljonen-Thor Görans (2:56)\r\n    13,Känslor Mellan Två-Thor Görans (3:19)\r\n    14,Kärlekens Labyrint-Thor Görans (3:09)\r\n    15,Min Seniorita-Thor Görans (3:15)\r\n    16,Varje Natt Och Dag-Thor Görans (2:46)\r\n    17,Mer Än Ord-Thor Görans (4:21)\r\n    18,En Pannini Och En Iskall Öl-Thor Görans (3:40)\r\n    19,Våran Kväll-Thor Görans (3:16)\r\n    20,Till Min Kära-Thor Görans (3:57)\r\n    21,Blixt Och Dunder-Thor Görans (3:00)\r\n    22,En Plats I Mitt Hjärta-Thor Görans (3:41)\r\n    23,Världens Under-Thor Görans (3:10)\r\n    24,I Mitt Innersta Hjärta-Thor Görans (2:30)\r\n    25,Om Du Vågar Och Vill-Thor Görans (2:27)\r\n    26,För Alltid Din-Thor Görans (2:44)\r\n    27,Ingen Som Du-Thor Görans (2:36)\r\n    28,Att Älska Så Här-Thor Görans (3:53)\r\n    29,Sol Och Öar, Vind Och Hav-Thor Görans (2:48)\r\n    30,Mannen I Mitt Liv-Thor Görans (3:53)\r\n    31,Judy-Thor Görans (2:35)\r\n    32,Tillbaka Igen-Thor Görans (2:43)\r\n    33,Bara Du Och Jag-Thor Görans (3:22)\r\n    34,En Solskenssång-Thor Görans (2:57)\r\n    35,Små Små Ord-Thor Görans (3:17)\r\n    36,Ändrade Planer-Thor Görans (3:44)\r\n    37,Jag Tror På Dig-Thor Görans (3:43)\r\n    38,Älskar Du Mig-Thor Görans (3:53)\r\n    39,Inget Mot Dig-Thor Görans (2:59)\r\n    40,Håll Mig Så Hårt I Din Famn-Thor Görans (3:35)\r\n    41,Till Min Kära (Specialversion)-Thor Görans (4:16)","torrent":{"xt":"urn:btih:a9d2393a7f1c1a0f212727d768847ee3a02b02f6","amp;dn":"Dansband-Thor+G%26ouml%3Brans-40+%26Aring%3Br+P%26aring%3B+V%26auml%3Bgarna","amp;tr":["udp%3A%2F%2Ftracker.leechers-paradise.org%3A6969","udp%3A%2F%2Fzer0day.ch%3A1337","udp%3A%2F%2Fopen.demonii.com%3A1337","udp%3A%2F%2Ftracker.coppersurfer.tk%3A6969","udp%3A%2F%2Fexodus.desync.com%3A6969"],"infoHash":"a9d2393a7f1c1a0f212727d768847ee3a02b02f6","infoHashBuffer":{"type":"Buffer","data":[169,210,57,58,127,28,26,15,33,39,39,215,104,132,126,227,160,43,2,246]},"announce":[],"urlList":[]}}