{"title":"AbbyWinters.14.11.07.Jada.Solo.XXX.720p.MP4-KTR","uid":11398524,"size":609786741,"categoryP":"porn","categoryS":"other","magnet":"?xt=urn:btih:bcb1633127f06905a9201c396611649f3059aed7&amp;dn=AbbyWinters.14.11.07.Jada.Solo.XXX.720p.MP4-KTR&amp;tr=udp%3A%2F%2Ftracker.openbittorrent.com%3A80&amp;tr=udp%3A%2F%2Fopen.demonii.com%3A1337&amp;tr=udp%3A%2F%2Ftracker.coppersurfer.tk%3A6969&amp;tr=udp%3A%2F%2Fexodus.desync.com%3A6969","seeders":1,"leechers":0,"uploader":"DrarbgXXX","files":3,"time":1415395277,"description":" &lt;a href=&quot;https://rarbg.com&quot; rel=&quot;nofollow&quot; target=&quot;_NEW&quot;&gt;https://rarbg.com&lt;/a&gt;\n\nAbbyWinters.14.11.07.Jada.Solo.XXX.720p.MP4-KTR\n-----------------------------------------\nScreens : &lt;a href=&quot;\nhttp://imgcrl.org/v/57380434457470400371/&quot; rel=&quot;nofollow&quot; target=&quot;_NEW&quot;&gt;\nhttp://imgcrl.org/v/57380434457470400371/&lt;/a&gt;\n\n-----------------------------------------\nAuto Media Info :\nVideo Format........: AVC\nCodec ID............: avc1\nLength..............: 17mn31s\nVideo...............: 1280x720 ( 25.000fps )\nBitrate.............: Variable\nAudio Format........: AAC\nCodec ID............: 40\nBit rate mode.......: Constant\nBitrate.............: 160Kbps\nChannel(s)..........: 2 channels","torrent":{"xt":"urn:btih:bcb1633127f06905a9201c396611649f3059aed7","amp;dn":"AbbyWinters.14.11.07.Jada.Solo.XXX.720p.MP4-KTR","amp;tr":["udp%3A%2F%2Ftracker.openbittorrent.com%3A80","udp%3A%2F%2Fopen.demonii.com%3A1337","udp%3A%2F%2Ftracker.coppersurfer.tk%3A6969","udp%3A%2F%2Fexodus.desync.com%3A6969"],"infoHash":"bcb1633127f06905a9201c396611649f3059aed7","infoHashBuffer":{"type":"Buffer","data":[188,177,99,49,39,240,105,5,169,32,28,57,102,17,100,159,48,89,174,215]},"announce":[],"urlList":[]}}