{"title":"Lets.Make.a.Deal.S05E130.2014.04.08.mp4","uid":9922939,"size":433541977,"categoryP":"video","categoryS":"tv_shows","magnet":"?xt=urn:btih:d242a781c926ac8a2552ff96ed4b4d1ae98f628c&amp;dn=Lets.Make.a.Deal.S05E130.2014.04.08.mp4&amp;tr=udp%3A%2F%2Ftracker.openbittorrent.com%3A80&amp;tr=udp%3A%2F%2Fopen.demonii.com%3A1337&amp;tr=udp%3A%2F%2Ftracker.coppersurfer.tk%3A6969&amp;tr=udp%3A%2F%2Fexodus.desync.com%3A6969","seeders":1,"leechers":1,"uploader":"Philandrist","files":-1,"time":1397020649,"description":"Episode Order: Season 05, Episode 130\nOriginal Air Date: April 08, 2014\n\nSeed and enjoy!","torrent":{"xt":"urn:btih:d242a781c926ac8a2552ff96ed4b4d1ae98f628c","amp;dn":"Lets.Make.a.Deal.S05E130.2014.04.08.mp4","amp;tr":["udp%3A%2F%2Ftracker.openbittorrent.com%3A80","udp%3A%2F%2Fopen.demonii.com%3A1337","udp%3A%2F%2Ftracker.coppersurfer.tk%3A6969","udp%3A%2F%2Fexodus.desync.com%3A6969"],"infoHash":"d242a781c926ac8a2552ff96ed4b4d1ae98f628c","infoHashBuffer":{"type":"Buffer","data":[210,66,167,129,201,38,172,138,37,82,255,150,237,75,77,26,233,143,98,140]},"announce":[],"urlList":[]}}