{"title":"DOPP-021 Reiko Sawamura, Takasaka Honami, Takasaka Masumi JAV CE","uid":11705212,"size":1476036075,"categoryP":"porn","categoryS":"movie_clips","magnet":"?xt=urn:btih:d722488f37e4667a49511086aa35b0f655890327&amp;dn=DOPP-021+Reiko+Sawamura%2C+Takasaka+Honami%2C+Takasaka+Masumi+JAV+CE&amp;tr=udp%3A%2F%2Ftracker.openbittorrent.com%3A80&amp;tr=udp%3A%2F%2Fopen.demonii.com%3A1337&amp;tr=udp%3A%2F%2Ftracker.coppersurfer.tk%3A6969&amp;tr=udp%3A%2F%2Fexodus.desync.com%3A6969","seeders":1,"leechers":0,"uploader":"3xplanet","files":1,"time":1424099650,"description":"DOPP-021 Reiko Sawamura, Takasaka Honami, Takasaka Masumi JAV CENSORED\nCover &lt;a href=&quot;\nhttp://www.3xplanet.com/view/78361.html&quot; rel=&quot;nofollow&quot; target=&quot;_NEW&quot;&gt;\nhttp://www.3xplanet.com/view/78361.html&lt;/a&gt;\nScreenshot &lt;a href=&quot;\nhttp://www.3xplanet.com/view/78439.html&quot; rel=&quot;nofollow&quot; target=&quot;_NEW&quot;&gt;\nhttp://www.3xplanet.com/view/78439.html&lt;/a&gt;\nTitle: \nStarring: Reiko Sawamura, Takasaka Honami, Takasaka Masumi\nStudio:  Takara Visual\n\nTag: JAV, CENSORED, Takara Visual, Work alone, Mature, housewife, drama","torrent":{"xt":"urn:btih:d722488f37e4667a49511086aa35b0f655890327","amp;dn":"DOPP-021+Reiko+Sawamura%2C+Takasaka+Honami%2C+Takasaka+Masumi+JAV+CE","amp;tr":["udp%3A%2F%2Ftracker.openbittorrent.com%3A80","udp%3A%2F%2Fopen.demonii.com%3A1337","udp%3A%2F%2Ftracker.coppersurfer.tk%3A6969","udp%3A%2F%2Fexodus.desync.com%3A6969"],"infoHash":"d722488f37e4667a49511086aa35b0f655890327","infoHashBuffer":{"type":"Buffer","data":[215,34,72,143,55,228,102,122,73,81,16,134,170,53,176,246,85,137,3,39]},"announce":[],"urlList":[]}}