{"title":"Snoopy come home - Hardcoded Greek subs","uid":4564862,"size":523991040,"categoryP":"video","categoryS":"movies","magnet":"?xt=urn:btih:dc73e32806914143367d69dc98c9a91bf5531390&amp;dn=Snoopy+come+home+-+Hardcoded+Greek+subs&amp;tr=udp%3A%2F%2Ftracker.openbittorrent.com%3A80&amp;tr=udp%3A%2F%2Fopen.demonii.com%3A1337&amp;tr=udp%3A%2F%2Ftracker.coppersurfer.tk%3A6969&amp;tr=udp%3A%2F%2Fexodus.desync.com%3A6969","seeders":1,"leechers":0,"uploader":"Groo_The_Wanderer","files":-1,"time":1228833398,"description":"Released in 1972. Snoopy travels to see his sick former owner and then feels obliged to return to her permanently.\n\nHardcoded Greek Subtitles\n\nIf anyone is having trouble playing the film :  &lt;a href=&quot;\nhttp://thepiratebay.se/torrent/4502169/VLC_Media_Player_0.9&quot; rel=&quot;nofollow&quot; target=&quot;_NEW&quot;&gt;\nhttp://thepiratebay.se/torrent/4502169/VLC_Media_Player_0.9&lt;/a&gt;\t\n","torrent":{"xt":"urn:btih:dc73e32806914143367d69dc98c9a91bf5531390","amp;dn":"Snoopy+come+home+-+Hardcoded+Greek+subs","amp;tr":["udp%3A%2F%2Ftracker.openbittorrent.com%3A80","udp%3A%2F%2Fopen.demonii.com%3A1337","udp%3A%2F%2Ftracker.coppersurfer.tk%3A6969","udp%3A%2F%2Fexodus.desync.com%3A6969"],"infoHash":"dc73e32806914143367d69dc98c9a91bf5531390","infoHashBuffer":{"type":"Buffer","data":[220,115,227,40,6,145,65,67,54,125,105,220,152,201,169,27,245,83,19,144]},"announce":[],"urlList":[]}}